autoGDC/__init__.py
autoGDC/autoGDC.py
autoGDC/collate.py
autoGDC/config.py
autoGDC/df_utils.py
autoGDC/download.py
autoGDC/store.py
autoGDC-0.0.1.dist-info/LICENSE.md
autoGDC-0.0.1.dist-info/METADATA
autoGDC-0.0.1.dist-info/WHEEL
autoGDC-0.0.1.dist-info/top_level.txt
autoGDC-0.0.1.dist-info/RECORD
