Metadata-Version: 2.1
Name: autoGDC
Version: 0.0.1
Summary: Automatic Genomic Data Commons processing for bioinformaticians
Home-page: https://gitlab.com/chase_brown/autogdc
Author: Chase Brown
Author-email: chase.brown.2016@gmail.com
License: UNKNOWN
Keywords: bioinformatics meta-analysis GDC Genomic-Data-Commons data-repository
Platform: UNKNOWN
Classifier: Development Status :: 1 - Planning
Classifier: Intended Audience :: Developers
Classifier: Topic :: Software Development :: Build Tools
Classifier: License :: OSI Approved :: MIT License
Classifier: Programming Language :: Python :: 3.5
Classifier: Programming Language :: Python :: 3.6
Requires-Dist: wrenlab
Requires-Dist: pandas
Requires-Dist: cruzdb @ git+git://github.com/brentp/cruzdb.git@pull16
Requires-Dist: oursql3 @ git+git://github.com/sqlobject/oursql.git@py3k
Requires-Dist: rpy2
